spectoprep/__init__.py
spectoprep/cli.py
spectoprep/spectoprep.py
spectoprep/modelling/ridge.py
spectoprep/pipeline/builder.py
spectoprep/pipeline/config.py
spectoprep/pipeline/optimizer.py
spectoprep/pipeline/utils.py
spectoprep/preprocessing/__init__.py
spectoprep/preprocessing/baseline.py
spectoprep/preprocessing/norml.py
spectoprep/preprocessing/scatter.py
spectoprep/preprocessing/smoothing.py
spectoprep/visualization/plots.py
spectoprep-1.0.1a0.dist-info/licenses/AUTHORS.rst
spectoprep-1.0.1a0.dist-info/licenses/LICENSE
spectoprep-1.0.1a0.dist-info/METADATA
spectoprep-1.0.1a0.dist-info/WHEEL
spectoprep-1.0.1a0.dist-info/top_level.txt
spectoprep-1.0.1a0.dist-info/RECORD
