Metadata-Version: 2.4
Name: spectoprep
Version: 1.0.1a0
Summary: A comprehensive spectral preprocessing toolkit for chemometrics
Author-email: Habeeb Babatunde <babatundehabeeb2@gmail.com>
Maintainer-email: Habeeb Babatunde <babatundehabeeb2@gmail.com>
License: MIT license
Project-URL: bugs, https://github.com/habeeb3579/spectoprep/issues
Project-URL: changelog, https://github.com/habeeb3579/spectoprep/blob/master/changelog.md
Project-URL: homepage, https://github.com/habeeb3579/spectoprep
Classifier: Programming Language :: Python :: 3
Classifier: License :: OSI Approved :: MIT License
Classifier: Operating System :: OS Independent
License-File: LICENSE
License-File: AUTHORS.rst
Requires-Dist: typer
Requires-Dist: bayesian-optimization
Requires-Dist: seaborn
Provides-Extra: dev
Requires-Dist: coverage; extra == "dev"
Requires-Dist: mypy; extra == "dev"
Requires-Dist: pytest; extra == "dev"
Requires-Dist: ruff; extra == "dev"
Requires-Dist: sphinx; extra == "dev"
Requires-Dist: myst-parser; extra == "dev"
Requires-Dist: furo; extra == "dev"
Requires-Dist: sphinx_rtd_theme; extra == "dev"
Requires-Dist: pydata-sphinx-theme; extra == "dev"
Requires-Dist: nbsphinx; extra == "dev"
Dynamic: license-file
